AnisCalculatrice/__init__.py
AnisCalculatrice-0.0.4.dist-info/LICENSE.txt
AnisCalculatrice-0.0.4.dist-info/METADATA
AnisCalculatrice-0.0.4.dist-info/WHEEL
AnisCalculatrice-0.0.4.dist-info/top_level.txt
AnisCalculatrice-0.0.4.dist-info/RECORD
