Metadata-Version: 2.1
Name: AnisCalculatrice
Version: 0.0.4
Summary: rien à dire
Author: kheirallah
Author-email: rida_kheirallah@yahoo.com
Classifier: Programming Language :: Python :: 3
Classifier: License :: OSI Approved :: MIT License
Classifier: Operating System :: OS Independent
License-File: LICENSE.txt
